MANIFEST.in
README
setup.py
skyarea.spec
bin/run_sky_area
debian/README.Debian
debian/changelog
debian/compat
debian/control
debian/copyright
debian/pydist-overrides
debian/rules
debian/watch
debian/source/format
sky_area/__init__.py
sky_area/eigenframe.py
sky_area/sky_area_clustering.py
skyarea.egg-info/PKG-INFO
skyarea.egg-info/SOURCES.txt
skyarea.egg-info/dependency_links.txt
skyarea.egg-info/requires.txt
skyarea.egg-info/top_level.txt