Metadata-Version: 1.1
Name: skyarea
Version: 0.3.2
Summary: Compute credible regions on the sky from RA-DEC MCMC samples
Home-page: http://farr.github.io/skyarea/
Author: Will M. Farr
Author-email: will.farr@ligo.org
License: MIT
Keywords: MCMC credible regions skymap LIGO
Platform: UNKNOWN
Classifier: Development Status :: 5 - Production/Stable
Classifier: Intended Audience :: Science/Research
Classifier: License :: OSI Approved :: MIT License
Classifier: Programming Language :: Python :: 2.7
Classifier: Topic :: Scientific/Engineering :: Astronomy
Classifier: Topic :: Scientific/Engineering :: Visualization
